themeengine/__init__.py
themeengine/admin.py
themeengine/api.py
themeengine/translation.py
themeengine/web_ui.py
themeengine/htdocs/admin.css
themeengine/htdocs/cycle2.css
themeengine/htdocs/default_screenshot.png
themeengine/htdocs/jquery.cycle2.min.js
themeengine/htdocs/jquery.rule-min.js
themeengine/htdocs/jquery.rule.js
themeengine/htdocs/no_screenshot.png
themeengine/htdocs/farbtastic/farbtastic.css
themeengine/htdocs/farbtastic/farbtastic.js
themeengine/htdocs/farbtastic/marker.png
themeengine/htdocs/farbtastic/mask.png
themeengine/htdocs/farbtastic/wheel.png
themeengine/htdocs/img/next.gif
themeengine/htdocs/img/prev.gif
themeengine/htdocs/img/spinner.gif
themeengine/locale/README.txt
themeengine/locale/es/LC_MESSAGES/themeengine.mo
themeengine/templates/admin_theme.html
themeengine/templates/admin_theme_advanced.html
themeengine/templates/admin_theme_advanced_jinja.html
themeengine/templates/admin_theme_custom.html
themeengine/templates/admin_theme_custom_jinja.html
themeengine/templates/admin_theme_jinja.html
TracThemeEngine-2.3.1.dist-info/COPYING
TracThemeEngine-2.3.1.dist-info/METADATA
TracThemeEngine-2.3.1.dist-info/WHEEL
TracThemeEngine-2.3.1.dist-info/entry_points.txt
TracThemeEngine-2.3.1.dist-info/top_level.txt
TracThemeEngine-2.3.1.dist-info/RECORD
