Metadata-Version: 2.1
Name: TracThemeEngine
Version: 2.3.1
Summary: Provide a modular interface to styling Trac
Home-page: https://trac-hacks.org/wiki/ThemeEnginePlugin
Author: Noah Kantrowitz
Author-email: noah@coderanger.net
Maintainer: Olemis Lang
Maintainer-email: olemis+trac@gmail.com
License: 3-Clause BSD
Download-URL: https://trac-hacks.org/svn/themeengineplugin/0.11#egg=TracThemeEngine-dev
Keywords: trac plugin theme style
Platform: UNKNOWN
Classifier: Framework :: Trac
Classifier: Development Status :: 5 - Production/Stable
Classifier: Environment :: Web Environment
Classifier: License :: OSI Approved :: BSD License
Classifier: Natural Language :: English
Classifier: Operating System :: OS Independent
Classifier: Programming Language :: Python
Requires-Dist: Trac
